reddit_regex_counter/__init__.py
reddit_regex_counter/__main__.py
reddit_regex_counter/redditDownloader.py
reddit_regex_counter/redditRegexCounter.py
reddit_regex_counter-0.0.2.dist-info/LICENSE
reddit_regex_counter-0.0.2.dist-info/METADATA
reddit_regex_counter-0.0.2.dist-info/WHEEL
reddit_regex_counter-0.0.2.dist-info/entry_points.txt
reddit_regex_counter-0.0.2.dist-info/top_level.txt
reddit_regex_counter-0.0.2.dist-info/RECORD
