Metadata-Version: 2.1
Name: reddit-regex-counter
Version: 0.0.2
Summary: Count the number of regex matches within a subreddit
Home-page: https://github.com/fangfufu/reddit-regex-counter
Author: Fufu Fang
Author-email: fangfufu2003@gmail.com
License: UNKNOWN
Project-URL: Bug Reports, https://github.com/fangfufu/reddit-regex-counter/issues
Project-URL: Source, https://github.com/fangfufu/reddit-regex-counter
Keywords: reddit
Platform: UNKNOWN
Classifier: Development Status :: 3 - Alpha
Classifier: Intended Audience :: Developers
Classifier: Topic :: Software Development :: Build Tools
Classifier: License :: OSI Approved :: GNU General Public License v3 or later (GPLv3+)
Classifier: Programming Language :: Python :: 3
Classifier: Programming Language :: Python :: 3.7
Classifier: Programming Language :: Python :: 3 :: Only
Requires-Python: >=3, <4
Requires-Dist: psaw
